{ "data": [{ "x": 0.363, "y": 0.032, "vx": 0.979, "vy": 0.205, "H_W": 0.683, "y_pred": 0.228 }, { "x": 0.566, "y": 0.605, "vx": -0.925, "vy": -0.38, "H_W": 0.683, "y_pred": 0.336 }, { "x": 0.416, "y": 0.814, "vx": 0.925, "vy": -0.38, "H_W": 0.683, "y_pred": 0.463 }, { "x": 0.603, "y": 0.978, "vx": -0.925, "vy": 0.38, "H_W": 0.683, "y_pred": 0.06 }, { "x": 0.858, "y": 0.029, "vx": 0.893, "vy": -0.45, "H_W": 0.683, "y_pred": 0.076 }, { "x": 0.297, "y": 0.969, "vx": 0.893, "vy": -0.45, "H_W": 0.683, "y_pred": 0.451 }, { "x": 0.264, "y": 0.092, "vx": -0.893, "vy": 0.45, "H_W": 0.683, "y_pred": 0.977 }, { "x": 0.893, "y": 0.672, "vx": -0.841, "vy": -0.541, "H_W": 0.683, "y_pred": 0.888 }, { "x": 0.419, "y": 0.689, "vx": 0.763, "vy": 0.647, "H_W": 0.683, "y_pred": 0.59 }, { "x": 0.352, "y": 0.214, "vx": -0.763, "vy": 0.647, "H_W": 0.683, "y_pred": 0.109 }, { "x": 0.81, "y": 0.155, "vx": 0.704, "vy": -0.71, "H_W": 0.683, "y_pred": 0.125 }, { "x": 0.309, "y": 0.071, "vx": -0.703, "vy": -0.711, "H_W": 0.683, "y_pred": 0.133 }, { "x": 0.728, "y": 0.27, "vx": 0.62, "vy": -0.784, "H_W": 0.683, "y_pred": 0.233 }, { "x": 0.272, "y": 0.421, "vx": -0.62, "vy": -0.784, "H_W": 0.683, "y_pred": 0.069 }, { "x": 0.565, "y": 0.182, "vx": 0.877, "vy": 0.48, "H_W": 0.683, "y_pred": 0.531 }, { "x": 0.608, "y": 0.448, "vx": -0.877, "vy": 0.48, "H_W": 0.683, "y_pred": 0.264 }, { "x": 0.806, "y": 0.42, "vx": 0.877, "vy": -0.48, "H_W": 0.683, "y_pred": 0.264 }, { "x": 0.206, "y": 0.743, "vx": 0.825, "vy": 0.566, "H_W": 0.683, "y_pred": 0.461 }, { "x": 0.464, "y": 0.076, "vx": -0.825, "vy": 0.566, "H_W": 0.683, "y_pred": 0.454 }, { "x": 0.813, "y": 0.49, "vx": 0.776, "vy": -0.631, "H_W": 0.683, "y_pred": 0.268 }, { "x": 0.686, "y": 0.485, "vx": -0.776, "vy": 0.631, "H_W": 0.683, "y_pred": 0.491 }, { "x": 0.5, "y": 0.075, "vx": 0.687, "vy": 0.727, "H_W": 0.683, "y_pred": 0.849 }, { "x": 0.394, "y": 0.211, "vx": -0.687, "vy": -0.727, "H_W": 0.683, "y_pred": 0.054 }, { "x": 0.626, "y": 0.389, "vx": 0.602, "vy": -0.799, "H_W": 0.683, "y_pred": 0.337 }, { "x": 0.404, "y": 0.507, "vx": -0.602, "vy": -0.799, "H_W": 0.683, "y_pred": 0.219 }, { "x": 0.566, "y": 0.624, "vx": 0.602, "vy": -0.799, "H_W": 0.683, "y_pred": 0.219 }, { "x": 0.464, "y": 0.741, "vx": -0.602, "vy": -0.799, "H_W": 0.683, "y_pred": 0.1 }, { "x": 0.437, "y": 0.79, "vx": 0.52, "vy": -0.854, "H_W": 0.683, "y_pred": 0.564 }, { "x": 0.725, "y": 0.775, "vx": -0.52, "vy": -0.854, "H_W": 0.683, "y_pred": 0.625 }, { "x": 0.199, "y": 0.403, "vx": -0.765, "vy": -0.644, "H_W": 0.683, "y_pred": 0.926 }, { "x": 0.241, "y": 0.674, "vx": 0.69, "vy": 0.724, "H_W": 0.683, "y_pred": 0.16 }, { "x": 0.648, "y": 0.382, "vx": -0.69, "vy": 0.724, "H_W": 0.683, "y_pred": 0.914 }, { "x": 0.404, "y": 0.163, "vx": 0.599, "vy": 0.801, "H_W": 0.683, "y_pred": 0.671 }, { "x": 0.631, "y": 0.051, "vx": -0.599, "vy": 0.801, "H_W": 0.683, "y_pred": 0.759 }, { "x": 0.305, "y": 0.03, "vx": 0.544, "vy": -0.839, "H_W": 0.683, "y_pred": 0.462 }, { "x": 0.818, "y": 0.052, "vx": -0.544, "vy": -0.839, "H_W": 0.683, "y_pred": 0.048 }, { "x": 0.708, "y": 0.64, "vx": 0.955, "vy": 0.297, "H_W": 0.683, "y_pred": 0.773 }, { "x": 0.255, "y": 0.711, "vx": 0.987, "vy": -0.159, "H_W": 0.683, "y_pred": 0.536 }, { "x": 0.154, "y": 0.336, "vx": -0.987, "vy": -0.159, "H_W": 0.683, "y_pred": 0.064 }, { "x": 0.611, "y": 0.934, "vx": -0.954, "vy": 0.299, "H_W": 0.683, "y_pred": 0.326 }, { "x": 0.505, "y": 0.831, "vx": 0.887, "vy": 0.462, "H_W": 0.683, "y_pred": 0.792 }, { "x": 0.636, "y": 0.991, "vx": -0.887, "vy": -0.462, "H_W": 0.683, "y_pred": 0.256 }, { "x": 0.759, "y": 0.034, "vx": -0.831, "vy": -0.557, "H_W": 0.683, "y_pred": 0.31 }, { "x": 0.58, "y": 0.722, "vx": 0.831, "vy": -0.557, "H_W": 0.683, "y_pred": 0.31 }, { "x": 0.63, "y": 0.387, "vx": -0.906, "vy": -0.424, "H_W": 0.683, "y_pred": 0.73 }, { "x": 0.829, "y": 0.613, "vx": 0.906, "vy": 0.424, "H_W": 0.683, "y_pred": 0.73 }, { "x": 0.288, "y": 0.387, "vx": 0.906, "vy": -0.424, "H_W": 0.683, "y_pred": 0.101 }, { "x": 0.252, "y": 0.613, "vx": -0.906, "vy": 0.424, "H_W": 0.683, "y_pred": 0.529 }, { "x": 0.721, "y": 0.666, "vx": -0.96, "vy": -0.28, "H_W": 0.683, "y_pred": 0.067 }, { "x": 0.778, "y": 0.179, "vx": 0.904, "vy": 0.428, "H_W": 0.683, "y_pred": 0.333 }, { "x": 0.214, "y": 0.76, "vx": 0.825, "vy": -0.566, "H_W": 0.683, "y_pred": 0.03 }, { "x": 0.408, "y": 0.451, "vx": -0.901, "vy": 0.434, "H_W": 0.683, "y_pred": 0.555 }, { "x": 0.897, "y": 0.743, "vx": -0.953, "vy": -0.304, "H_W": 0.683, "y_pred": 0.143 }, { "x": 0.59, "y": 0.991, "vx": -0.866, "vy": 0.5, "H_W": 0.683, "y_pred": 0.333 }, { "x": 0.876, "y": 0.054, "vx": 0.943, "vy": -0.334, "H_W": 0.683, "y_pred": 0.01 }, { "x": 0.285, "y": 0.798, "vx": 0.603, "vy": 0.798, "H_W": 0.683, "y_pred": 0.183 }, { "x": 0.744, "y": 0.679, "vx": -0.603, "vy": 0.798, "H_W": 0.683, "y_pred": 0.06 }, { "x": 0.202, "y": 0.586, "vx": 0.536, "vy": 0.844, "H_W": 0.683, "y_pred": 0.425 }, { "x": 0.691, "y": 0.645, "vx": 0.466, "vy": 0.885, "H_W": 0.683, "y_pred": 0.497 }, { "x": 0.558, "y": 0.731, "vx": -0.466, "vy": 0.885, "H_W": 0.683, "y_pred": 0.943 }, { "x": 0.172, "y": 0.832, "vx": 0.414, "vy": 0.91, "H_W": 0.683, "y_pred": 0.501 }, { "x": 0.839, "y": 0.979, "vx": 0.414, "vy": 0.91, "H_W": 0.683, "y_pred": 0.501 }, { "x": 0.495, "y": 0.874, "vx": -0.414, "vy": -0.91, "H_W": 0.683, "y_pred": 0.059 }, { "x": 0.517, "y": 0.633, "vx": -0.788, "vy": 0.616, "H_W": 0.683, "y_pred": 0.367 }, { "x": 0.256, "y": 0.503, "vx": 0.721, "vy": -0.692, "H_W": 0.683, "y_pred": 0.542 }, { "x": 0.582, "y": 0.87, "vx": -0.721, "vy": -0.692, "H_W": 0.683, "y_pred": 0.649 }, { "x": 0.665, "y": 0.698, "vx": -0.989, "vy": 0.145, "H_W": 0.683, "y_pred": 0.944 }, { "x": 0.552, "y": 0.166, "vx": 0.856, "vy": -0.517, "H_W": 0.683, "y_pred": 0.23 }, { "x": 0.197, "y": 0.949, "vx": -0.804, "vy": 0.595, "H_W": 0.683, "y_pred": 0.246 }, { "x": 0.878, "y": 0.777, "vx": -0.86, "vy": 0.511, "H_W": 0.683, "y_pred": 0.411 }, { "x": 0.507, "y": 0.018, "vx": 0.86, "vy": -0.511, "H_W": 0.683, "y_pred": 0.411 }, { "x": 0.108, "y": 0.812, "vx": -0.86, "vy": -0.511, "H_W": 0.683, "y_pred": 0.151 }, { "x": 0.618, "y": 0.08, "vx": -0.93, "vy": 0.367, "H_W": 0.683, "y_pred": 0.987 }, { "x": 0.71, "y": 0.801, "vx": -0.889, "vy": 0.457, "H_W": 0.683, "y_pred": 0.087 }, { "x": 0.764, "y": 0.26, "vx": 0.941, "vy": -0.339, "H_W": 0.683, "y_pred": 0.135 }, { "x": 0.181, "y": 0.006, "vx": 0.946, "vy": 0.323, "H_W": 0.683, "y_pred": 0.415 }, { "x": 0.294, "y": 0.767, "vx": -0.946, "vy": 0.323, "H_W": 0.683, "y_pred": 0.586 }, { "x": 0.719, "y": 0.757, "vx": -0.985, "vy": -0.171, "H_W": 0.683, "y_pred": 0.32 }, { "x": 0.594, "y": 0.483, "vx": 0.67, "vy": -0.742, "H_W": 0.683, "y_pred": 0.175 }, { "x": 0.326, "y": 0.733, "vx": -0.67, "vy": -0.742, "H_W": 0.683, "y_pred": 0.583 }, { "x": 0.832, "y": 0.903, "vx": 0.741, "vy": 0.672, "H_W": 0.683, "y_pred": 0.874 }, { "x": 0.672, "y": 0.123, "vx": -0.807, "vy": -0.591, "H_W": 0.683, "y_pred": 0.33 }, { "x": 0.688, "y": 0.871, "vx": 0.885, "vy": -0.466, "H_W": 0.683, "y_pred": 0.63 }, { "x": 0.121, "y": 0.203, "vx": 0.949, "vy": 0.314, "H_W": 0.683, "y_pred": 0.629 }, { "x": 0.349, "y": 0.944, "vx": -0.949, "vy": 0.314, "H_W": 0.683, "y_pred": 0.403 }, { "x": 0.37, "y": 0.894, "vx": 0.955, "vy": 0.295, "H_W": 0.683, "y_pred": 0.821 }, { "x": 0.366, "y": 0.369, "vx": -0.955, "vy": 0.295, "H_W": 0.683, "y_pred": 0.986 }, { "x": 0.787, "y": 0.818, "vx": -0.988, "vy": 0.157, "H_W": 0.683, "y_pred": 0.765 }, { "x": 0.779, "y": 0.649, "vx": 0.955, "vy": -0.295, "H_W": 0.683, "y_pred": 0.548 }, { "x": 0.894, "y": 0.327, "vx": -0.738, "vy": 0.675, "H_W": 0.683, "y_pred": 0.86 }, { "x": 0.295, "y": 0.082, "vx": 0.738, "vy": -0.675, "H_W": 0.683, "y_pred": 0.86 }, { "x": 0.515, "y": 0.491, "vx": -0.738, "vy": -0.675, "H_W": 0.683, "y_pred": 0.464 }, { "x": 0.472, "y": 0.83, "vx": 0.738, "vy": 0.675, "H_W": 0.683, "y_pred": 0.464 }, { "x": 0.339, "y": 0.421, "vx": -0.738, "vy": 0.675, "H_W": 0.683, "y_pred": 0.211 }, { "x": 0.744, "y": 0.161, "vx": 0.645, "vy": 0.764, "H_W": 0.683, "y_pred": 0.605 }, { "x": 0.216, "y": 0.037, "vx": -0.645, "vy": -0.764, "H_W": 0.683, "y_pred": 0.072 }, { "x": 0.25, "y": 0.493, "vx": 0.722, "vy": -0.692, "H_W": 0.683, "y_pred": 0.559 }, { "x": 0.587, "y": 0.862, "vx": -0.722, "vy": -0.692, "H_W": 0.683, "y_pred": 0.638 }, { "x": 0.577, "y": 0.769, "vx": 0.722, "vy": 0.692, "H_W": 0.683, "y_pred": 0.638 }, { "x": 0.259, "y": 0.4, "vx": -0.722, "vy": 0.692, "H_W": 0.683, "y_pred": 0.165 }, { "x": 0.357, "y": 0.962, "vx": 0.858, "vy": -0.514, "H_W": 0.683, "y_pred": 0.398 }, { "x": 0.26, "y": 0.25, "vx": -0.858, "vy": 0.514, "H_W": 0.683, "y_pred": 0.646 }, { "x": 0.698, "y": 0.198, "vx": 0.773, "vy": 0.634, "H_W": 0.683, "y_pred": 0.561 }, { "x": 0.684, "y": 0.928, "vx": -0.856, "vy": 0.518, "H_W": 0.683, "y_pred": 0.419 }, { "x": 0.695, "y": 0.149, "vx": 0.856, "vy": 0.518, "H_W": 0.683, "y_pred": 0.419 }, { "x": 0.633, "y": 0.776, "vx": -0.806, "vy": 0.593, "H_W": 0.683, "y_pred": 0.533 }, { "x": 0.588, "y": 0.715, "vx": -0.946, "vy": 0.324, "H_W": 0.683, "y_pred": 0.49 }, { "x": 0.529, "y": 0.582, "vx": 0.746, "vy": -0.665, "H_W": 0.683, "y_pred": 0.032 }, { "x": 0.173, "y": 0.804, "vx": -0.844, "vy": 0.536, "H_W": 0.683, "y_pred": 0.107 }, { "x": 0.122, "y": 0.626, "vx": -0.924, "vy": 0.383, "H_W": 0.683, "y_pred": 0.693 }, { "x": 0.578, "y": 0.7, "vx": -0.961, "vy": -0.276, "H_W": 0.683, "y_pred": 0.036 }, { "x": 0.19, "y": 0.065, "vx": 0.841, "vy": -0.54, "H_W": 0.683, "y_pred": 0.696 }, { "x": 0.454, "y": 0.791, "vx": -0.841, "vy": -0.54, "H_W": 0.683, "y_pred": 0.576 }, { "x": 0.433, "y": 0.727, "vx": 0.848, "vy": -0.529, "H_W": 0.683, "y_pred": 0.209 }, { "x": 0.199, "y": 0.521, "vx": -0.848, "vy": 0.529, "H_W": 0.683, "y_pred": 0.384 }, { "x": 0.726, "y": 0.534, "vx": -0.927, "vy": -0.376, "H_W": 0.683, "y_pred": 0.491 }, { "x": 0.813, "y": 0.126, "vx": 0.982, "vy": 0.188, "H_W": 0.683, "y_pred": 0.179 }, { "x": 0.346, "y": 0.17, "vx": 0.855, "vy": -0.518, "H_W": 0.683, "y_pred": 0.409 }, { "x": 0.275, "y": 0.949, "vx": -0.855, "vy": -0.518, "H_W": 0.683, "y_pred": 0.181 }, { "x": 0.795, "y": 0.03, "vx": -0.934, "vy": -0.358, "H_W": 0.683, "y_pred": 0.976 }, { "x": 0.746, "y": 0.628, "vx": 0.982, "vy": 0.19, "H_W": 0.683, "y_pred": 0.7 }, { "x": 0.328, "y": 0.924, "vx": 0.982, "vy": -0.19, "H_W": 0.683, "y_pred": 0.733 }, { "x": 0.508, "y": 0.027, "vx": -0.982, "vy": -0.19, "H_W": 0.683, "y_pred": 0.4 }, { "x": 0.593, "y": 0.866, "vx": 0.886, "vy": -0.464, "H_W": 0.683, "y_pred": 0.554 }, { "x": 0.823, "y": 0.529, "vx": -0.807, "vy": -0.591, "H_W": 0.683, "y_pred": 0.576 }, { "x": 0.423, "y": 0.956, "vx": 0.714, "vy": 0.7, "H_W": 0.683, "y_pred": 0.217 }, { "x": 0.425, "y": 0.606, "vx": -0.714, "vy": 0.7, "H_W": 0.683, "y_pred": 0.648 }, { "x": 0.726, "y": 0.256, "vx": 0.714, "vy": 0.7, "H_W": 0.683, "y_pred": 0.648 }, { "x": 0.123, "y": 0.095, "vx": -0.714, "vy": -0.7, "H_W": 0.683, "y_pred": 0.486 }, { "x": 0.887, "y": 0.582, "vx": -0.773, "vy": -0.635, "H_W": 0.683, "y_pred": 0.314 }, { "x": 0.345, "y": 0.937, "vx": 0.744, "vy": 0.668, "H_W": 0.683, "y_pred": 0.203 }, { "x": 0.456, "y": 0.512, "vx": -0.744, "vy": 0.668, "H_W": 0.683, "y_pred": 0.423 }, { "x": 0.744, "y": 0.087, "vx": 0.744, "vy": 0.668, "H_W": 0.683, "y_pred": 0.423 }, { "x": 0.114, "y": 0.02, "vx": -0.775, "vy": -0.632, "H_W": 0.683, "y_pred": 0.69 }, { "x": 0.865, "y": 0.529, "vx": -0.775, "vy": -0.632, "H_W": 0.683, "y_pred": 0.3 }, { "x": 0.342, "y": 0.973, "vx": 0.69, "vy": -0.724, "H_W": 0.683, "y_pred": 0.036 }, { "x": 0.48, "y": 0.627, "vx": -0.792, "vy": 0.611, "H_W": 0.683, "y_pred": 0.297 }, { "x": 0.849, "y": 0.761, "vx": 0.994, "vy": 0.109, "H_W": 0.683, "y_pred": 0.785 }, { "x": 0.451, "y": 0.981, "vx": 0.994, "vy": -0.109, "H_W": 0.683, "y_pred": 0.893 }, { "x": 0.346, "y": 0.465, "vx": -0.994, "vy": -0.109, "H_W": 0.683, "y_pred": 0.248 }, { "x": 0.744, "y": 0.207, "vx": -0.994, "vy": -0.109, "H_W": 0.683, "y_pred": 0.074 }, { "x": 0.858, "y": 0.051, "vx": 0.994, "vy": 0.109, "H_W": 0.683, "y_pred": 0.074 }, { "x": 0.45, "y": 0.394, "vx": 0.97, "vy": 0.243, "H_W": 0.683, "y_pred": 0.596 }, { "x": 0.507, "y": 0.099, "vx": -0.918, "vy": -0.395, "H_W": 0.683, "y_pred": 0.85 }, { "x": 0.383, "y": 0.613, "vx": -0.852, "vy": -0.524, "H_W": 0.683, "y_pred": 0.633 }, { "x": 0.421, "y": 0.912, "vx": 0.653, "vy": -0.757, "H_W": 0.683, "y_pred": 0.071 }, { "x": 0.527, "y": 0.874, "vx": -0.653, "vy": 0.757, "H_W": 0.683, "y_pred": 0.535 }, { "x": 0.474, "y": 0.719, "vx": 0.588, "vy": 0.809, "H_W": 0.683, "y_pred": 0.225 }, { "x": 0.577, "y": 0.625, "vx": -0.588, "vy": 0.809, "H_W": 0.683, "y_pred": 0.203 }, { "x": 0.46, "y": 0.37, "vx": -0.798, "vy": 0.602, "H_W": 0.683, "y_pred": 0.017 }, { "x": 0.763, "y": 0.948, "vx": -0.991, "vy": -0.132, "H_W": 0.683, "y_pred": 0.606 }, { "x": 0.835, "y": 0.638, "vx": 0.991, "vy": -0.132, "H_W": 0.683, "y_pred": 0.606 }, { "x": 0.432, "y": 0.327, "vx": 0.991, "vy": -0.132, "H_W": 0.683, "y_pred": 0.217 }, { "x": 0.412, "y": 0.584, "vx": -0.967, "vy": 0.254, "H_W": 0.683, "y_pred": 0.874 }, { "x": 0.853, "y": 0.818, "vx": -0.967, "vy": -0.254, "H_W": 0.683, "y_pred": 0.107 }, { "x": 0.706, "y": 0.22, "vx": 0.967, "vy": -0.254, "H_W": 0.683, "y_pred": 0.107 }, { "x": 0.716, "y": 0.835, "vx": 0.854, "vy": 0.52, "H_W": 0.683, "y_pred": 0.912 }, { "x": 0.663, "y": 0.139, "vx": -0.814, "vy": -0.581, "H_W": 0.683, "y_pred": 0.401 }, { "x": 0.648, "y": 0.768, "vx": 0.814, "vy": -0.581, "H_W": 0.683, "y_pred": 0.401 }, { "x": 0.73, "y": 0.026, "vx": -0.814, "vy": -0.581, "H_W": 0.683, "y_pred": 0.217 }, { "x": 0.518, "y": 0.543, "vx": 0.724, "vy": -0.69, "H_W": 0.683, "y_pred": 0.129 }, { "x": 0.315, "y": 0.916, "vx": -0.724, "vy": -0.69, "H_W": 0.683, "y_pred": 0.917 }, { "x": 0.157, "y": 0.646, "vx": 0.74, "vy": 0.672, "H_W": 0.683, "y_pred": 0.234 }, { "x": 0.65, "y": 0.231, "vx": -0.74, "vy": 0.672, "H_W": 0.683, "y_pred": 0.423 }, { "x": 0.543, "y": 0.184, "vx": 0.74, "vy": -0.672, "H_W": 0.683, "y_pred": 0.423 }, { "x": 0.264, "y": 0.599, "vx": -0.74, "vy": -0.672, "H_W": 0.683, "y_pred": 0.92 }, { "x": 0.816, "y": 0.853, "vx": 0.649, "vy": -0.761, "H_W": 0.683, "y_pred": 0.537 }, { "x": 0.138, "y": 0.941, "vx": -0.649, "vy": 0.761, "H_W": 0.683, "y_pred": 0.894 }, { "x": 0.225, "y": 0.139, "vx": 0.662, "vy": 0.749, "H_W": 0.683, "y_pred": 0.579 }, { "x": 0.707, "y": 0.094, "vx": -0.662, "vy": -0.749, "H_W": 0.683, "y_pred": 0.731 }, { "x": 0.36, "y": 0.328, "vx": 0.662, "vy": -0.749, "H_W": 0.683, "y_pred": 0.731 }, { "x": 0.572, "y": 0.562, "vx": -0.662, "vy": -0.749, "H_W": 0.683, "y_pred": 0.04 }, { "x": 0.439, "y": 0.729, "vx": 0.586, "vy": -0.81, "H_W": 0.683, "y_pred": 0.408 }, { "x": 0.617, "y": 0.818, "vx": -0.586, "vy": -0.81, "H_W": 0.683, "y_pred": 0.456 }, { "x": 0.606, "y": 0.4, "vx": 0.99, "vy": 0.142, "H_W": 0.683, "y_pred": 0.482 }, { "x": 0.201, "y": 0.735, "vx": 0.99, "vy": 0.142, "H_W": 0.683, "y_pred": 0.902 }, { "x": 0.203, "y": 0.931, "vx": -0.99, "vy": -0.142, "H_W": 0.683, "y_pred": 0.678 }, { "x": 0.257, "y": 0.207, "vx": -0.769, "vy": 0.64, "H_W": 0.683, "y_pred": 0.262 }, { "x": 0.877, "y": 0.122, "vx": 0.687, "vy": -0.727, "H_W": 0.683, "y_pred": 0.068 }, { "x": 0.488, "y": 0.995, "vx": 0.818, "vy": 0.575, "H_W": 0.683, "y_pred": 0.478 }, { "x": 0.194, "y": 0.351, "vx": -0.818, "vy": 0.575, "H_W": 0.683, "y_pred": 0.421 }, { "x": 0.802, "y": 0.463, "vx": -0.872, "vy": -0.49, "H_W": 0.683, "y_pred": 0.98 }, { "x": 0.279, "y": 0.435, "vx": 0.968, "vy": -0.251, "H_W": 0.683, "y_pred": 0.161 }, { "x": 0.161, "y": 0.157, "vx": -0.968, "vy": 0.251, "H_W": 0.683, "y_pred": 0.598 }, { "x": 0.724, "y": 0.042, "vx": 0.498, "vy": 0.867, "H_W": 0.683, "y_pred": 0.745 }, { "x": 0.473, "y": 0.087, "vx": -0.498, "vy": 0.867, "H_W": 0.683, "y_pred": 0.158 }, { "x": 0.393, "y": 0.071, "vx": 0.595, "vy": 0.803, "H_W": 0.683, "y_pred": 0.732 }, { "x": 0.647, "y": 0.035, "vx": -0.595, "vy": -0.803, "H_W": 0.683, "y_pred": 0.782 }, { "x": 0.312, "y": 0.14, "vx": 0.595, "vy": -0.803, "H_W": 0.683, "y_pred": 0.782 }, { "x": 0.728, "y": 0.246, "vx": -0.595, "vy": -0.803, "H_W": 0.683, "y_pred": 0.833 }, { "x": 0.231, "y": 0.351, "vx": 0.595, "vy": -0.803, "H_W": 0.683, "y_pred": 0.833 }, { "x": 0.81, "y": 0.457, "vx": -0.595, "vy": -0.803, "H_W": 0.683, "y_pred": 0.883 }, { "x": 0.15, "y": 0.562, "vx": 0.595, "vy": -0.803, "H_W": 0.683, "y_pred": 0.883 }, { "x": 0.891, "y": 0.668, "vx": -0.595, "vy": -0.803, "H_W": 0.683, "y_pred": 0.933 }, { "x": 0.745, "y": 0.572, "vx": 0.907, "vy": -0.422, "H_W": 0.683, "y_pred": 0.398 }, { "x": 0.508, "y": 0.693, "vx": 0.956, "vy": 0.294, "H_W": 0.683, "y_pred": 0.914 }, { "x": 0.513, "y": 0.45, "vx": -0.895, "vy": 0.447, "H_W": 0.683, "y_pred": 0.445 }, { "x": 0.847, "y": 0.296, "vx": 0.815, "vy": -0.58, "H_W": 0.683, "y_pred": 0.136 }, { "x": 0.292, "y": 0.373, "vx": 0.953, "vy": -0.302, "H_W": 0.683, "y_pred": 0.045 }, { "x": 0.223, "y": 0.523, "vx": -0.894, "vy": 0.449, "H_W": 0.683, "y_pred": 0.578 }, { "x": 0.783, "y": 0.419, "vx": -0.894, "vy": -0.449, "H_W": 0.683, "y_pred": 0.891 }, { "x": 0.657, "y": 0.639, "vx": 0.894, "vy": 0.449, "H_W": 0.683, "y_pred": 0.891 }, { "x": 0.583, "y": 0.948, "vx": -0.823, "vy": -0.567, "H_W": 0.683, "y_pred": 0.648 }, { "x": 0.744, "y": 0.39, "vx": 0.823, "vy": 0.567, "H_W": 0.683, "y_pred": 0.648 }, { "x": 0.602, "y": 0.934, "vx": -0.823, "vy": -0.567, "H_W": 0.683, "y_pred": 0.681 }, { "x": 0.725, "y": 0.404, "vx": 0.823, "vy": 0.567, "H_W": 0.683, "y_pred": 0.681 }, { "x": 0.621, "y": 0.92, "vx": -0.823, "vy": -0.567, "H_W": 0.683, "y_pred": 0.714 }, { "x": 0.706, "y": 0.418, "vx": 0.823, "vy": 0.567, "H_W": 0.683, "y_pred": 0.714 }, { "x": 0.64, "y": 0.907, "vx": -0.823, "vy": -0.567, "H_W": 0.683, "y_pred": 0.747 }, { "x": 0.687, "y": 0.431, "vx": 0.823, "vy": 0.567, "H_W": 0.683, "y_pred": 0.747 }, { "x": 0.79, "y": 0.655, "vx": -0.669, "vy": -0.743, "H_W": 0.683, "y_pred": 0.25 }, { "x": 0.588, "y": 0.222, "vx": -0.938, "vy": -0.345, "H_W": 0.683, "y_pred": 0.632 }, { "x": 0.457, "y": 0.703, "vx": 0.984, "vy": -0.18, "H_W": 0.683, "y_pred": 0.557 }, { "x": 0.397, "y": 0.285, "vx": -0.944, "vy": 0.33, "H_W": 0.683, "y_pred": 1 }, { "x": 0.529, "y": 0.252, "vx": 0.902, "vy": 0.431, "H_W": 0.683, "y_pred": 0.581 }, { "x": 0.582, "y": 0.339, "vx": -0.861, "vy": 0.509, "H_W": 0.683, "y_pred": 0.291 }, { "x": 0.736, "y": 0.312, "vx": 0.787, "vy": -0.617, "H_W": 0.683, "y_pred": 0.008 }, { "x": 0.105, "y": 0.656, "vx": 0.934, "vy": -0.359, "H_W": 0.683, "y_pred": 0.153 }, { "x": 0.39, "y": 0.19, "vx": -0.934, "vy": 0.359, "H_W": 0.683, "y_pred": 0.971 }, { "x": 0.885, "y": 0.995, "vx": -0.894, "vy": -0.447, "H_W": 0.683, "y_pred": 0.385 }, { "x": 0.557, "y": 0.06, "vx": 0.894, "vy": 0.447, "H_W": 0.683, "y_pred": 0.385 }, { "x": 0.561, "y": 0.17, "vx": -0.894, "vy": 0.447, "H_W": 0.683, "y_pred": 0.687 }, { "x": 0.88, "y": 0.775, "vx": 0.894, "vy": -0.447, "H_W": 0.683, "y_pred": 0.687 }, { "x": 0.868, "y": 0.762, "vx": 0.77, "vy": -0.638, "H_W": 0.683, "y_pred": 0.602 }, { "x": 0.351, "y": 0.671, "vx": -0.895, "vy": 0.445, "H_W": 0.683, "y_pred": 0.346 }, { "x": 0.35, "y": 0.763, "vx": 0.83, "vy": -0.558, "H_W": 0.683, "y_pred": 0.123 }, { "x": 0.313, "y": 0.553, "vx": -0.83, "vy": 0.558, "H_W": 0.683, "y_pred": 0.155 }, { "x": 0.324, "y": 0.745, "vx": 0.744, "vy": -0.668, "H_W": 0.683, "y_pred": 0.143 }, { "x": 0.477, "y": 0.83, "vx": -0.744, "vy": 0.668, "H_W": 0.683, "y_pred": 0.77 }, { "x": 0.638, "y": 0.528, "vx": 0.656, "vy": 0.754, "H_W": 0.683, "y_pred": 0.863 }, { "x": 0.305, "y": 0.307, "vx": -0.656, "vy": 0.754, "H_W": 0.683, "y_pred": 0.5 }, { "x": 0.388, "y": 0.423, "vx": 0.925, "vy": -0.38, "H_W": 0.683, "y_pred": 0.055 }, { "x": 0.122, "y": 0.473, "vx": -0.925, "vy": 0.38, "H_W": 0.683, "y_pred": 0.852 }, { "x": 0.631, "y": 0.63, "vx": -0.925, "vy": -0.38, "H_W": 0.683, "y_pred": 0.35 }, { "x": 0.796, "y": 0.449, "vx": 0.856, "vy": 0.516, "H_W": 0.683, "y_pred": 0.628 }, { "x": 0.177, "y": 0.334, "vx": 0.856, "vy": -0.516, "H_W": 0.683, "y_pred": 0.392 }, { "x": 0.443, "y": 0.883, "vx": -0.856, "vy": 0.516, "H_W": 0.683, "y_pred": 0.156 }, { "x": 0.671, "y": 0.284, "vx": -0.972, "vy": 0.235, "H_W": 0.683, "y_pred": 0.874 }, { "x": 0.895, "y": 0.837, "vx": 0.972, "vy": 0.235, "H_W": 0.683, "y_pred": 0.874 }, { "x": 0.462, "y": 0.609, "vx": 0.972, "vy": -0.235, "H_W": 0.683, "y_pred": 0.419 }, { "x": 0.483, "y": 0.849, "vx": -0.924, "vy": 0.382, "H_W": 0.683, "y_pred": 0.254 }, { "x": 0.526, "y": 0.504, "vx": 0.981, "vy": 0.193, "H_W": 0.683, "y_pred": 0.64 }, { "x": 0.624, "y": 0.444, "vx": 0.76, "vy": -0.65, "H_W": 0.683, "y_pred": 0.026 }, { "x": 0.756, "y": 0.29, "vx": -0.743, "vy": 0.669, "H_W": 0.683, "y_pred": 0.602 }, { "x": 0.421, "y": 0.102, "vx": 0.708, "vy": -0.706, "H_W": 0.683, "y_pred": 0.742 }, { "x": 0.437, "y": 0.438, "vx": -0.708, "vy": -0.706, "H_W": 0.683, "y_pred": 0.343 }, { "x": 0.825, "y": 0.238, "vx": -0.905, "vy": -0.426, "H_W": 0.683, "y_pred": 0.982 }, { "x": 0.633, "y": 0.765, "vx": 0.905, "vy": 0.426, "H_W": 0.683, "y_pred": 0.982 }, { "x": 0.166, "y": 0.532, "vx": 0.967, "vy": -0.253, "H_W": 0.683, "y_pred": 0.212 }, { "x": 0.275, "y": 0.066, "vx": -0.967, "vy": 0.253, "H_W": 0.683, "y_pred": 0.555 }, { "x": 0.781, "y": 0.939, "vx": -0.918, "vy": 0.396, "H_W": 0.683, "y_pred": 0.061 }, { "x": 0.699, "y": 0.128, "vx": 0.918, "vy": -0.396, "H_W": 0.683, "y_pred": 0.061 }, { "x": 0.179, "y": 0.805, "vx": 0.918, "vy": 0.396, "H_W": 0.683, "y_pred": 0.678 }, { "x": 0.341, "y": 0.262, "vx": -0.918, "vy": -0.396, "H_W": 0.683, "y_pred": 0.583 }, { "x": 0.403, "y": 0.199, "vx": 0.842, "vy": 0.539, "H_W": 0.683, "y_pred": 0.758 }, { "x": 0.24, "y": 0.53, "vx": -0.842, "vy": -0.539, "H_W": 0.683, "y_pred": 0.631 }, { "x": 0.882, "y": 0.741, "vx": -0.842, "vy": 0.539, "H_W": 0.683, "y_pred": 0.504 }, { "x": 0.505, "y": 0.065, "vx": 0.897, "vy": -0.443, "H_W": 0.683, "y_pred": 0.293 }, { "x": 0.524, "y": 0.269, "vx": -0.95, "vy": -0.313, "H_W": 0.683, "y_pred": 0.467 }, { "x": 0.175, "y": 0.191, "vx": 0.989, "vy": -0.145, "H_W": 0.683, "y_pred": 0.014 }, { "x": 0.263, "y": 0.35, "vx": -0.947, "vy": 0.321, "H_W": 0.683, "y_pred": 0.977 }, { "x": 0.698, "y": 0.808, "vx": -0.852, "vy": -0.523, "H_W": 0.683, "y_pred": 0.715 }, { "x": 0.643, "y": 0.497, "vx": 0.811, "vy": 0.585, "H_W": 0.683, "y_pred": 0.874 }, { "x": 0.839, "y": 0.569, "vx": -0.749, "vy": -0.662, "H_W": 0.683, "y_pred": 0.191 }, { "x": 0.326, "y": 0.945, "vx": 0.66, "vy": -0.751, "H_W": 0.683, "y_pred": 0.178 }, { "x": 0.61, "y": 0.827, "vx": -0.66, "vy": 0.751, "H_W": 0.683, "y_pred": 0.492 }, { "x": 0.586, "y": 0.698, "vx": -0.975, "vy": 0.222, "H_W": 0.683, "y_pred": 0.772 }, { "x": 0.687, "y": 0.885, "vx": -0.937, "vy": 0.35, "H_W": 0.683, "y_pred": 0.194 }, { "x": 0.823, "y": 0.291, "vx": 0.937, "vy": -0.35, "H_W": 0.683, "y_pred": 0.194 }, { "x": 0.333, "y": 0.534, "vx": 0.937, "vy": 0.35, "H_W": 0.683, "y_pred": 0.898 }, { "x": 0.157, "y": 0.641, "vx": -0.937, "vy": -0.35, "H_W": 0.683, "y_pred": 0.009 }, { "x": 0.488, "y": 0.726, "vx": -0.757, "vy": 0.654, "H_W": 0.683, "y_pred": 0.607 }, { "x": 0.665, "y": 0.37, "vx": 0.687, "vy": 0.727, "H_W": 0.683, "y_pred": 0.889 }, { "x": 0.229, "y": 0.084, "vx": -0.687, "vy": 0.727, "H_W": 0.683, "y_pred": 0.012 }, { "x": 0.771, "y": 0.069, "vx": 0.603, "vy": -0.798, "H_W": 0.683, "y_pred": 0.374 }, { "x": 0.258, "y": 0.188, "vx": -0.603, "vy": -0.798, "H_W": 0.683, "y_pred": 0.249 }, { "x": 0.713, "y": 0.306, "vx": 0.603, "vy": -0.798, "H_W": 0.683, "y_pred": 0.249 }, { "x": 0.315, "y": 0.425, "vx": -0.603, "vy": -0.798, "H_W": 0.683, "y_pred": 0.123 }, { "x": 0.656, "y": 0.543, "vx": 0.603, "vy": -0.798, "H_W": 0.683, "y_pred": 0.123 }, { "x": 0.373, "y": 0.662, "vx": -0.603, "vy": -0.798, "H_W": 0.683, "y_pred": 0.002 }, { "x": 0.669, "y": 0.866, "vx": 0.674, "vy": -0.738, "H_W": 0.683, "y_pred": 0.335 }, { "x": 0.245, "y": 0.876, "vx": -0.674, "vy": 0.738, "H_W": 0.683, "y_pred": 0.87 }, { "x": 0.323, "y": 0.461, "vx": 0.955, "vy": 0.296, "H_W": 0.683, "y_pred": 0.768 }, { "x": 0.137, "y": 0.841, "vx": -0.955, "vy": -0.296, "H_W": 0.683, "y_pred": 0.325 }, { "x": 0.598, "y": 0.143, "vx": -0.955, "vy": -0.296, "H_W": 0.683, "y_pred": 0.581 }, { "x": 0.331, "y": 0.898, "vx": 0.983, "vy": 0.183, "H_W": 0.683, "y_pred": 0.92 }, { "x": 0.5, "y": 0.24, "vx": -0.983, "vy": -0.183, "H_W": 0.683, "y_pred": 0.169 }, { "x": 0.54, "y": 0.717, "vx": 0.905, "vy": -0.425, "H_W": 0.683, "y_pred": 0.401 }, { "x": 0.579, "y": 0.618, "vx": -0.834, "vy": -0.553, "H_W": 0.683, "y_pred": 0.913 }, { "x": 0.685, "y": 0.836, "vx": 0.745, "vy": 0.667, "H_W": 0.683, "y_pred": 0.75 }, { "x": 0.115, "y": 0.41, "vx": -0.745, "vy": 0.667, "H_W": 0.683, "y_pred": 0.127 }, { "x": 0.116, "y": 0.189, "vx": 0.69, "vy": -0.724, "H_W": 0.683, "y_pred": 0.831 }, { "x": 0.772, "y": 0.481, "vx": -0.69, "vy": -0.724, "H_W": 0.683, "y_pred": 0.241 }, { "x": 0.296, "y": 0.721, "vx": 0.601, "vy": -0.799, "H_W": 0.683, "y_pred": 0.649 }, { "x": 0.735, "y": 0.836, "vx": -0.601, "vy": -0.799, "H_W": 0.683, "y_pred": 0.543 }, { "x": 0.208, "y": 0.926, "vx": 0.538, "vy": -0.843, "H_W": 0.683, "y_pred": 0.89 }, { "x": 0.361, "y": 0.715, "vx": 0.788, "vy": -0.616, "H_W": 0.683, "y_pred": 0.017 }, { "x": 0.295, "y": 0.568, "vx": -0.883, "vy": 0.469, "H_W": 0.683, "y_pred": 0.425 }, { "x": 0.872, "y": 0.325, "vx": -0.883, "vy": -0.469, "H_W": 0.683, "y_pred": 0.869 }, { "x": 0.595, "y": 0.628, "vx": 0.955, "vy": 0.298, "H_W": 0.683, "y_pred": 0.812 }, { "x": 0.138, "y": 0.703, "vx": 0.992, "vy": -0.125, "H_W": 0.683, "y_pred": 0.544 }, { "x": 0.263, "y": 0.408, "vx": -0.992, "vy": -0.125, "H_W": 0.683, "y_pred": 0.175 }, { "x": 0.681, "y": 0.035, "vx": -0.98, "vy": 0.201, "H_W": 0.683, "y_pred": 0.539 }, { "x": 0.898, "y": 0.508, "vx": 0.98, "vy": 0.201, "H_W": 0.683, "y_pred": 0.539 }, { "x": 0.477, "y": 0.981, "vx": 0.98, "vy": 0.201, "H_W": 0.683, "y_pred": 0.862 }, { "x": 0.366, "y": 0.072, "vx": -0.98, "vy": -0.201, "H_W": 0.683, "y_pred": 0.338 }, { "x": 0.716, "y": 0.626, "vx": -0.801, "vy": 0.599, "H_W": 0.683, "y_pred": 0.504 }, { "x": 0.748, "y": 0.459, "vx": -0.914, "vy": -0.405, "H_W": 0.683, "y_pred": 0.674 }, { "x": 0.755, "y": 0.384, "vx": 0.951, "vy": 0.308, "H_W": 0.683, "y_pred": 0.499 }, { "x": 0.272, "y": 0.832, "vx": 0.894, "vy": -0.447, "H_W": 0.683, "y_pred": 0.299 }, { "x": 0.287, "y": 0.224, "vx": -0.894, "vy": 0.447, "H_W": 0.683, "y_pred": 0.834 }, { "x": 0.846, "y": 0.721, "vx": -0.894, "vy": -0.447, "H_W": 0.683, "y_pred": 0.63 }, { "x": 0.595, "y": 0.334, "vx": 0.894, "vy": 0.447, "H_W": 0.683, "y_pred": 0.63 }, { "x": 0.522, "y": 0.444, "vx": -0.894, "vy": 0.447, "H_W": 0.683, "y_pred": 0.441 }, { "x": 0.328, "y": 0.234, "vx": -0.833, "vy": 0.553, "H_W": 0.683, "y_pred": 0.478 }, { "x": 0.358, "y": 0.839, "vx": 0.833, "vy": 0.553, "H_W": 0.683, "y_pred": 0.538 }, { "x": 0.299, "y": 0.142, "vx": -0.833, "vy": 0.553, "H_W": 0.683, "y_pred": 0.598 }, { "x": 0.388, "y": 0.747, "vx": 0.833, "vy": 0.553, "H_W": 0.683, "y_pred": 0.659 }, { "x": 0.269, "y": 0.05, "vx": -0.833, "vy": 0.553, "H_W": 0.683, "y_pred": 0.719 }, { "x": 0.417, "y": 0.656, "vx": 0.833, "vy": 0.553, "H_W": 0.683, "y_pred": 0.779 }, { "x": 0.24, "y": 0.041, "vx": -0.833, "vy": -0.553, "H_W": 0.683, "y_pred": 0.839 }, { "x": 0.896, "y": 0.739, "vx": -0.833, "vy": -0.553, "H_W": 0.683, "y_pred": 0.899 }, { "x": 0.447, "y": 0.564, "vx": 0.833, "vy": 0.553, "H_W": 0.683, "y_pred": 0.899 }, { "x": 0.21, "y": 0.133, "vx": -0.833, "vy": -0.553, "H_W": 0.683, "y_pred": 0.959 }, { "x": 0.854, "y": 0.865, "vx": -0.921, "vy": -0.39, "H_W": 0.683, "y_pred": 0.285 }, { "x": 0.327, "y": 0.917, "vx": 0.708, "vy": 0.706, "H_W": 0.683, "y_pred": 0.101 }, { "x": 0.532, "y": 0.582, "vx": -0.708, "vy": 0.706, "H_W": 0.683, "y_pred": 0.816 }, { "x": 0.761, "y": 0.946, "vx": -0.926, "vy": 0.379, "H_W": 0.683, "y_pred": 0 }, { "x": 0.186, "y": 0.124, "vx": 0.679, "vy": -0.734, "H_W": 0.683, "y_pred": 0.835 }, { "x": 0.72, "y": 0.392, "vx": -0.679, "vy": -0.734, "H_W": 0.683, "y_pred": 0.33 }, { "x": 0.374, "y": 0.661, "vx": 0.679, "vy": -0.734, "H_W": 0.683, "y_pred": 0.33 }, { "x": 0.532, "y": 0.93, "vx": -0.679, "vy": -0.734, "H_W": 0.683, "y_pred": 0.505 }, { "x": 0.407, "y": 0.265, "vx": -0.979, "vy": 0.206, "H_W": 0.683, "y_pred": 0.698 }, { "x": 0.295, "y": 0.346, "vx": -0.95, "vy": -0.311, "H_W": 0.683, "y_pred": 0.275 }, { "x": 0.621, "y": 0.345, "vx": 0.803, "vy": 0.596, "H_W": 0.683, "y_pred": 0.757 }, { "x": 0.211, "y": 0.944, "vx": 0.675, "vy": -0.738, "H_W": 0.683, "y_pred": 0.319 }, { "x": 0.701, "y": 0.797, "vx": -0.675, "vy": 0.738, "H_W": 0.683, "y_pred": 0.48 }, { "x": 0.419, "y": 0.755, "vx": 0.98, "vy": 0.201, "H_W": 0.683, "y_pred": 0.929 }, { "x": 0.424, "y": 0.299, "vx": -0.98, "vy": -0.201, "H_W": 0.683, "y_pred": 0.128 }, { "x": 0.845, "y": 0.175, "vx": -0.98, "vy": 0.201, "H_W": 0.683, "y_pred": 0.728 }, { "x": 0.734, "y": 0.648, "vx": 0.98, "vy": 0.201, "H_W": 0.683, "y_pred": 0.728 }, { "x": 0.313, "y": 0.878, "vx": 0.98, "vy": -0.201, "H_W": 0.683, "y_pred": 0.672 }, { "x": 0.109, "y": 0.405, "vx": -0.98, "vy": -0.201, "H_W": 0.683, "y_pred": 0.072 }, { "x": 0.53, "y": 0.069, "vx": -0.98, "vy": 0.201, "H_W": 0.683, "y_pred": 0.527 }, { "x": 0.297, "y": 0.013, "vx": 0.768, "vy": -0.64, "H_W": 0.683, "y_pred": 0.844 }, { "x": 0.465, "y": 0.503, "vx": -0.768, "vy": -0.64, "H_W": 0.683, "y_pred": 0.716 }, { "x": 0.772, "y": 0.993, "vx": 0.768, "vy": -0.64, "H_W": 0.683, "y_pred": 0.716 }, { "x": 0.866, "y": 0.203, "vx": -0.788, "vy": 0.615, "H_W": 0.683, "y_pred": 0.335 }, { "x": 0.404, "y": 0.346, "vx": 0.788, "vy": -0.615, "H_W": 0.683, "y_pred": 0.335 }, { "x": 0.325, "y": 0.895, "vx": -0.788, "vy": -0.615, "H_W": 0.683, "y_pred": 0.619 }, { "x": 0.238, "y": 0.163, "vx": -0.727, "vy": 0.687, "H_W": 0.683, "y_pred": 0.126 }, { "x": 0.617, "y": 0.678, "vx": 0.957, "vy": 0.29, "H_W": 0.683, "y_pred": 0.848 }, { "x": 0.159, "y": 0.639, "vx": 0.957, "vy": -0.29, "H_W": 0.683, "y_pred": 0.266 }, { "x": 0.298, "y": 0.044, "vx": -0.957, "vy": 0.29, "H_W": 0.683, "y_pred": 0.619 }, { "x": 0.362, "y": 0.341, "vx": -0.965, "vy": -0.263, "H_W": 0.683, "y_pred": 0.202 }, { "x": 0.807, "y": 0.278, "vx": -0.965, "vy": 0.263, "H_W": 0.683, "y_pred": 0.998 }, { "x": 0.718, "y": 0.977, "vx": 0.927, "vy": -0.374, "H_W": 0.683, "y_pred": 0.811 }, { "x": 0.197, "y": 0.047, "vx": 0.855, "vy": -0.519, "H_W": 0.683, "y_pred": 0.667 }, { "x": 0.426, "y": 0.823, "vx": -0.855, "vy": -0.519, "H_W": 0.683, "y_pred": 0.445 }, { "x": 0.422, "y": 0.721, "vx": 0.97, "vy": 0.242, "H_W": 0.683, "y_pred": 0.932 }, { "x": 0.45, "y": 0.138, "vx": -0.97, "vy": -0.242, "H_W": 0.683, "y_pred": 0.391 }, { "x": 0.184, "y": 0.96, "vx": -0.666, "vy": 0.746, "H_W": 0.683, "y_pred": 0.898 }, { "x": 0.671, "y": 0.334, "vx": -0.994, "vy": -0.112, "H_W": 0.683, "y_pred": 0.06 }, { "x": 0.874, "y": 0.025, "vx": -0.871, "vy": 0.491, "H_W": 0.683, "y_pred": 0.429 }, { "x": 0.53, "y": 0.816, "vx": 0.871, "vy": -0.491, "H_W": 0.683, "y_pred": 0.429 }, { "x": 0.663, "y": 0.5, "vx": -0.871, "vy": -0.491, "H_W": 0.683, "y_pred": 0.872 }, { "x": 0.741, "y": 0.658, "vx": 0.871, "vy": 0.491, "H_W": 0.683, "y_pred": 0.872 }, { "x": 0.145, "y": 0.183, "vx": 0.871, "vy": -0.491, "H_W": 0.683, "y_pred": 0.522 }, { "x": 0.452, "y": 0.975, "vx": -0.871, "vy": 0.491, "H_W": 0.683, "y_pred": 0.173 }, { "x": 0.475, "y": 0.619, "vx": -0.893, "vy": 0.45, "H_W": 0.683, "y_pred": 0.292 }, { "x": 0.62, "y": 0.464, "vx": -0.944, "vy": 0.329, "H_W": 0.683, "y_pred": 0.711 }, { "x": 0.395, "y": 0.112, "vx": 0.877, "vy": 0.481, "H_W": 0.683, "y_pred": 0.598 }, { "x": 0.192, "y": 0.754, "vx": -0.877, "vy": -0.481, "H_W": 0.683, "y_pred": 0.203 }, { "x": 0.729, "y": 0.222, "vx": -0.864, "vy": 0.503, "H_W": 0.683, "y_pred": 0.307 }, { "x": 0.664, "y": 0.593, "vx": 0.864, "vy": -0.503, "H_W": 0.683, "y_pred": 0.307 }, { "x": 0.55, "y": 0.221, "vx": -0.864, "vy": -0.503, "H_W": 0.683, "y_pred": 0.902 }, { "x": 0.843, "y": 0.964, "vx": 0.864, "vy": 0.503, "H_W": 0.683, "y_pred": 0.902 }, { "x": 0.216, "y": 0.193, "vx": 0.788, "vy": 0.616, "H_W": 0.683, "y_pred": 0.91 }, { "x": 0.514, "y": 0.355, "vx": -0.788, "vy": -0.616, "H_W": 0.683, "y_pred": 0.621 }, { "x": 0.17, "y": 0.07, "vx": 0.814, "vy": 0.581, "H_W": 0.683, "y_pred": 0.937 }, { "x": 0.518, "y": 0.559, "vx": -0.814, "vy": -0.581, "H_W": 0.683, "y_pred": 0.972 }, { "x": 0.793, "y": 0.811, "vx": 0.814, "vy": 0.581, "H_W": 0.683, "y_pred": 0.972 }, { "x": 0.221, "y": 0.106, "vx": 0.9, "vy": -0.436, "H_W": 0.683, "y_pred": 0.446 }, { "x": 0.329, "y": 0.922, "vx": -0.9, "vy": 0.436, "H_W": 0.683, "y_pred": 0.137 }, { "x": 0.878, "y": 0.05, "vx": -0.9, "vy": -0.436, "H_W": 0.683, "y_pred": 0.719 }, { "x": 0.572, "y": 0.977, "vx": 0.9, "vy": 0.436, "H_W": 0.683, "y_pred": 0.719 }, { "x": 0.527, "y": 0.967, "vx": -0.9, "vy": -0.436, "H_W": 0.683, "y_pred": 0.115 }, { "x": 0.343, "y": 0.835, "vx": 0.824, "vy": -0.567, "H_W": 0.683, "y_pred": 0.174 }, { "x": 0.329, "y": 0.501, "vx": -0.824, "vy": 0.567, "H_W": 0.683, "y_pred": 0.161 }, { "x": 0.9, "y": 0.02, "vx": 0.742, "vy": 0.67, "H_W": 0.683, "y_pred": 0.152 }, { "x": 0.233, "y": 0.531, "vx": -0.85, "vy": -0.527, "H_W": 0.683, "y_pred": 0.587 }, { "x": 0.3, "y": 0.646, "vx": 0.888, "vy": 0.461, "H_W": 0.683, "y_pred": 0.823 }, { "x": 0.269, "y": 0.268, "vx": -0.888, "vy": -0.461, "H_W": 0.683, "y_pred": 0.696 }, { "x": 0.839, "y": 0.819, "vx": -0.888, "vy": 0.461, "H_W": 0.683, "y_pred": 0.215 }, { "x": 0.841, "y": 0.114, "vx": -0.897, "vy": -0.442, "H_W": 0.683, "y_pred": 0.785 }, { "x": 0.604, "y": 0.929, "vx": 0.897, "vy": 0.442, "H_W": 0.683, "y_pred": 0.785 }, { "x": 0.505, "y": 0.985, "vx": -0.897, "vy": -0.442, "H_W": 0.683, "y_pred": 0.101 }, { "x": 0.352, "y": 0.816, "vx": 0.817, "vy": -0.577, "H_W": 0.683, "y_pred": 0.146 }, { "x": 0.332, "y": 0.545, "vx": -0.817, "vy": 0.577, "H_W": 0.683, "y_pred": 0.078 }, { "x": 0.3, "y": 0.734, "vx": 0.817, "vy": -0.577, "H_W": 0.683, "y_pred": 0.01 }, { "x": 0.445, "y": 0.737, "vx": -0.735, "vy": 0.678, "H_W": 0.683, "y_pred": 0.688 }, { "x": 0.665, "y": 0.442, "vx": 0.661, "vy": 0.751, "H_W": 0.683, "y_pred": 0.998 }, { "x": 0.352, "y": 0.308, "vx": -0.586, "vy": 0.811, "H_W": 0.683, "y_pred": 0.955 }, { "x": 0.196, "y": 0.566, "vx": 0.869, "vy": -0.495, "H_W": 0.683, "y_pred": 0.105 }, { "x": 0.404, "y": 0.602, "vx": -0.869, "vy": 0.495, "H_W": 0.683, "y_pred": 0.227 }, { "x": 0.39, "y": 0.082, "vx": -0.902, "vy": 0.432, "H_W": 0.683, "y_pred": 0.944 }, { "x": 0.859, "y": 0.791, "vx": -0.968, "vy": 0.252, "H_W": 0.683, "y_pred": 0.5 }, { "x": 0.7, "y": 0.614, "vx": 0.968, "vy": -0.252, "H_W": 0.683, "y_pred": 0.5 }, { "x": 0.247, "y": 0.037, "vx": 0.917, "vy": 0.399, "H_W": 0.683, "y_pred": 0.516 }, { "x": 0.276, "y": 0.977, "vx": -0.917, "vy": 0.399, "H_W": 0.683, "y_pred": 0.21 }, { "x": 0.798, "y": 0.082, "vx": -0.917, "vy": -0.399, "H_W": 0.683, "y_pred": 0.937 }, { "x": 0.717, "y": 0.048, "vx": -0.788, "vy": 0.615, "H_W": 0.683, "y_pred": 0.009 }, { "x": 0.502, "y": 0.417, "vx": 0.715, "vy": -0.699, "H_W": 0.683, "y_pred": 0.295 }, { "x": 0.345, "y": 0.768, "vx": -0.715, "vy": -0.699, "H_W": 0.683, "y_pred": 0.844 }, { "x": 0.711, "y": 0.992, "vx": 0.63, "vy": -0.777, "H_W": 0.683, "y_pred": 0.471 }, { "x": 0.274, "y": 0.839, "vx": -0.63, "vy": 0.777, "H_W": 0.683, "y_pred": 0.864 }, { "x": 0.742, "y": 0.67, "vx": 0.63, "vy": 0.777, "H_W": 0.683, "y_pred": 0.864 }, { "x": 0.243, "y": 0.501, "vx": -0.63, "vy": 0.777, "H_W": 0.683, "y_pred": 0.743 }, { "x": 0.64, "y": 0.627, "vx": -0.971, "vy": -0.239, "H_W": 0.683, "y_pred": 0.036 }, { "x": 0.883, "y": 0.126, "vx": 0.927, "vy": 0.375, "H_W": 0.683, "y_pred": 0.195 }, { "x": 0.377, "y": 0.99, "vx": 0.927, "vy": -0.375, "H_W": 0.683, "y_pred": 0.621 }, { "x": 0.129, "y": 0.106, "vx": -0.927, "vy": -0.375, "H_W": 0.683, "y_pred": 0.563 }, { "x": 0.73, "y": 0.94, "vx": -0.862, "vy": -0.506, "H_W": 0.683, "y_pred": 0.546 }, { "x": 0.659, "y": 0.254, "vx": 0.862, "vy": 0.506, "H_W": 0.683, "y_pred": 0.546 }, { "x": 0.442, "y": 0.256, "vx": -0.971, "vy": 0.239, "H_W": 0.683, "y_pred": 0.775 }, { "x": 0.877, "y": 0.82, "vx": -0.971, "vy": 0.239, "H_W": 0.683, "y_pred": 0.504 }, { "x": 0.66, "y": 0.05, "vx": -0.849, "vy": -0.529, "H_W": 0.683, "y_pred": 0.536 }, { "x": 0.649, "y": 0.682, "vx": 0.777, "vy": -0.629, "H_W": 0.683, "y_pred": 0.266 }, { "x": 0.142, "y": 0.186, "vx": 0.785, "vy": 0.62, "H_W": 0.683, "y_pred": 0.823 }, { "x": 0.593, "y": 0.353, "vx": -0.785, "vy": -0.62, "H_W": 0.683, "y_pred": 0.514 }, { "x": 0.672, "y": 0.892, "vx": 0.785, "vy": -0.62, "H_W": 0.683, "y_pred": 0.514 }, { "x": 0.204, "y": 0.084, "vx": 0.633, "vy": -0.774, "H_W": 0.683, "y_pred": 0.659 }, { "x": 0.776, "y": 0.258, "vx": -0.633, "vy": -0.774, "H_W": 0.683, "y_pred": 0.923 }, { "x": 0.269, "y": 0.466, "vx": 0.705, "vy": -0.709, "H_W": 0.683, "y_pred": 0.609 }, { "x": 0.594, "y": 0.794, "vx": -0.705, "vy": -0.709, "H_W": 0.683, "y_pred": 0.449 }, { "x": 0.366, "y": 0.916, "vx": 0.823, "vy": 0.568, "H_W": 0.683, "y_pred": 0.444 }, { "x": 0.308, "y": 0.255, "vx": -0.823, "vy": 0.568, "H_W": 0.683, "y_pred": 0.424 }, { "x": 0.515, "y": 0.254, "vx": 0.968, "vy": -0.251, "H_W": 0.683, "y_pred": 0.07 }, { "x": 0.365, "y": 0.928, "vx": -0.968, "vy": 0.251, "H_W": 0.683, "y_pred": 0.554 }, { "x": 0.846, "y": 0.292, "vx": -0.934, "vy": -0.356, "H_W": 0.683, "y_pred": 0.738 }, { "x": 0.691, "y": 0.387, "vx": 0.98, "vy": 0.198, "H_W": 0.683, "y_pred": 0.479 }, { "x": 0.271, "y": 0.853, "vx": 0.98, "vy": 0.198, "H_W": 0.683, "y_pred": 0.931 }, { "x": 0.149, "y": 0.681, "vx": -0.98, "vy": -0.198, "H_W": 0.683, "y_pred": 0.341 }, { "x": 0.57, "y": 0.214, "vx": -0.98, "vy": -0.198, "H_W": 0.683, "y_pred": 0.249 }, { "x": 0.59, "y": 0.718, "vx": 0.98, "vy": 0.198, "H_W": 0.683, "y_pred": 0.839 }, { "x": 0.17, "y": 0.816, "vx": 0.98, "vy": -0.198, "H_W": 0.683, "y_pred": 0.571 }, { "x": 0.251, "y": 0.35, "vx": -0.98, "vy": -0.198, "H_W": 0.683, "y_pred": 0.019 }, { "x": 0.52, "y": 0.28, "vx": -0.961, "vy": 0.275, "H_W": 0.683, "y_pred": 0.915 }, { "x": 0.402, "y": 0.235, "vx": 0.843, "vy": 0.538, "H_W": 0.683, "y_pred": 0.794 }, { "x": 0.24, "y": 0.497, "vx": -0.843, "vy": -0.538, "H_W": 0.683, "y_pred": 0.661 }, { "x": 0.313, "y": 0.42, "vx": 0.854, "vy": 0.52, "H_W": 0.683, "y_pred": 0.969 }, { "x": 0.252, "y": 0.524, "vx": -0.926, "vy": -0.376, "H_W": 0.683, "y_pred": 0.22 }, { "x": 0.759, "y": 0.363, "vx": -0.926, "vy": 0.376, "H_W": 0.683, "y_pred": 0.591 }, { "x": 0.675, "y": 0.578, "vx": 0.851, "vy": -0.524, "H_W": 0.683, "y_pred": 0.285 }, { "x": 0.458, "y": 0.458, "vx": -0.925, "vy": -0.379, "H_W": 0.683, "y_pred": 0.415 }, { "x": 0.337, "y": 0.129, "vx": 0.893, "vy": -0.45, "H_W": 0.683, "y_pred": 0.359 }, { "x": 0.224, "y": 0.932, "vx": -0.893, "vy": 0.45, "H_W": 0.683, "y_pred": 0.166 }, { "x": 0.702, "y": 0.306, "vx": -0.954, "vy": -0.299, "H_W": 0.683, "y_pred": 0.476 }, { "x": 0.304, "y": 0.772, "vx": -0.404, "vy": 0.915, "H_W": 0.683, "y_pred": 0.903 }, { "x": 0.717, "y": 0.905, "vx": -0.829, "vy": 0.559, "H_W": 0.683, "y_pred": 0.599 }, { "x": 0.557, "y": 0.339, "vx": 0.746, "vy": 0.666, "H_W": 0.683, "y_pred": 0.916 }, { "x": 0.24, "y": 0.092, "vx": -0.746, "vy": -0.666, "H_W": 0.683, "y_pred": 0.473 }, { "x": 0.748, "y": 0.076, "vx": -0.978, "vy": -0.208, "H_W": 0.683, "y_pred": 0.466 }, { "x": 0.466, "y": 0.847, "vx": -0.933, "vy": -0.36, "H_W": 0.683, "y_pred": 0.019 }, { "x": 0.408, "y": 0.739, "vx": 0.943, "vy": -0.334, "H_W": 0.683, "y_pred": 0.432 }, { "x": 0.508, "y": 0.605, "vx": -0.973, "vy": 0.231, "H_W": 0.683, "y_pred": 0.871 }, { "x": 0.539, "y": 0.121, "vx": 0.913, "vy": 0.407, "H_W": 0.683, "y_pred": 0.421 }, { "x": 0.429, "y": 0.33, "vx": -0.969, "vy": -0.248, "H_W": 0.683, "y_pred": 0.207 }, { "x": 0.868, "y": 0.256, "vx": -0.969, "vy": 0.248, "H_W": 0.683, "y_pred": 0.957 }, { "x": 0.693, "y": 0.842, "vx": 0.969, "vy": 0.248, "H_W": 0.683, "y_pred": 0.957 }, { "x": 0.196, "y": 0.318, "vx": 0.924, "vy": -0.383, "H_W": 0.683, "y_pred": 0.17 }, { "x": 0.315, "y": 0.585, "vx": -0.924, "vy": 0.383, "H_W": 0.683, "y_pred": 0.617 }, { "x": 0.827, "y": 0.511, "vx": -0.924, "vy": -0.383, "H_W": 0.683, "y_pred": 0.597 }, { "x": 0.662, "y": 0.392, "vx": 0.924, "vy": 0.383, "H_W": 0.683, "y_pred": 0.597 }, { "x": 0.151, "y": 0.705, "vx": 0.924, "vy": -0.383, "H_W": 0.683, "y_pred": 0.189 }, { "x": 0.361, "y": 0.198, "vx": -0.924, "vy": 0.383, "H_W": 0.683, "y_pred": 0.976 }, { "x": 0.866, "y": 0.927, "vx": -0.973, "vy": -0.233, "H_W": 0.683, "y_pred": 0.273 }, { "x": 0.701, "y": 0.378, "vx": 0.973, "vy": -0.233, "H_W": 0.683, "y_pred": 0.273 }, { "x": 0.164, "y": 0.402, "vx": 0.591, "vy": 0.807, "H_W": 0.683, "y_pred": 0.072 }, { "x": 0.884, "y": 0.304, "vx": -0.591, "vy": 0.807, "H_W": 0.683, "y_pred": 0.067 }, { "x": 0.8, "y": 0.113, "vx": -0.695, "vy": -0.719, "H_W": 0.683, "y_pred": 0.612 }, { "x": 0.359, "y": 0.48, "vx": 0.783, "vy": -0.622, "H_W": 0.683, "y_pred": 0.265 }, { "x": 0.379, "y": 0.986, "vx": -0.783, "vy": 0.622, "H_W": 0.683, "y_pred": 0.587 }, { "x": 0.798, "y": 0.592, "vx": 0.707, "vy": 0.708, "H_W": 0.683, "y_pred": 0.888 }, { "x": 0.315, "y": 0.376, "vx": -0.867, "vy": 0.498, "H_W": 0.683, "y_pred": 0.519 }, { "x": 0.572, "y": 0.663, "vx": 0.986, "vy": 0.167, "H_W": 0.683, "y_pred": 0.769 }, { "x": 0.161, "y": 0.944, "vx": 0.986, "vy": -0.167, "H_W": 0.683, "y_pred": 0.736 }, { "x": 0.25, "y": 0.551, "vx": -0.986, "vy": -0.167, "H_W": 0.683, "y_pred": 0.242 }, { "x": 0.862, "y": 0.431, "vx": -0.838, "vy": -0.546, "H_W": 0.683, "y_pred": 0.655 }, { "x": 0.453, "y": 0.927, "vx": 0.777, "vy": 0.629, "H_W": 0.683, "y_pred": 0.425 }, { "x": 0.294, "y": 0.411, "vx": -0.777, "vy": 0.629, "H_W": 0.683, "y_pred": 0.056 }, { "x": 0.88, "y": 0.022, "vx": 0.714, "vy": 0.701, "H_W": 0.683, "y_pred": 0.194 }, { "x": 0.647, "y": 0.59, "vx": -0.842, "vy": -0.539, "H_W": 0.683, "y_pred": 0.954 }, { "x": 0.233, "y": 0.137, "vx": 0.966, "vy": -0.259, "H_W": 0.683, "y_pred": 0.164 }, { "x": 0.21, "y": 0.474, "vx": -0.966, "vy": 0.259, "H_W": 0.683, "y_pred": 0.949 }, { "x": 0.576, "y": 0.434, "vx": -0.934, "vy": 0.357, "H_W": 0.683, "y_pred": 0.684 }, { "x": 0.867, "y": 0.532, "vx": 0.872, "vy": -0.49, "H_W": 0.683, "y_pred": 0.423 }, { "x": 0.272, "y": 0.624, "vx": 0.872, "vy": 0.49, "H_W": 0.683, "y_pred": 0.777 }, { "x": 0.323, "y": 0.221, "vx": -0.872, "vy": -0.49, "H_W": 0.683, "y_pred": 0.868 }, { "x": 0.486, "y": 0.091, "vx": 0.872, "vy": 0.49, "H_W": 0.683, "y_pred": 0.514 }, { "x": 0.109, "y": 0.753, "vx": -0.872, "vy": -0.49, "H_W": 0.683, "y_pred": 0.16 }, { "x": 0.705, "y": 0.403, "vx": -0.872, "vy": 0.49, "H_W": 0.683, "y_pred": 0.195 }, { "x": 0.123, "y": 0.914, "vx": 0.847, "vy": 0.531, "H_W": 0.683, "y_pred": 0.282 }, { "x": 0.512, "y": 0.166, "vx": -0.847, "vy": 0.531, "H_W": 0.683, "y_pred": 0.447 }, { "x": 0.765, "y": 0.405, "vx": 0.758, "vy": -0.652, "H_W": 0.683, "y_pred": 0.109 }, { "x": 0.791, "y": 0.669, "vx": -0.758, "vy": 0.652, "H_W": 0.683, "y_pred": 0.922 }, { "x": 0.385, "y": 0.275, "vx": 0.677, "vy": 0.736, "H_W": 0.683, "y_pred": 0.748 }, { "x": 0.523, "y": 0.01, "vx": -0.677, "vy": 0.736, "H_W": 0.683, "y_pred": 0.431 }, { "x": 0.12, "y": 0.62, "vx": 0.801, "vy": -0.599, "H_W": 0.683, "y_pred": 0.344 }, { "x": 0.59, "y": 0.793, "vx": -0.801, "vy": 0.599, "H_W": 0.683, "y_pred": 0.533 }, { "x": 0.642, "y": 0.308, "vx": 0.734, "vy": 0.679, "H_W": 0.683, "y_pred": 0.792 }, { "x": 0.175, "y": 0.091, "vx": -0.734, "vy": -0.679, "H_W": 0.683, "y_pred": 0.498 }, { "x": 0.627, "y": 0.857, "vx": 0.885, "vy": 0.466, "H_W": 0.683, "y_pred": 0.856 }, { "x": 0.52, "y": 0.947, "vx": -0.885, "vy": -0.466, "H_W": 0.683, "y_pred": 0.223 }, { "x": 0.304, "y": 0.686, "vx": 0.81, "vy": -0.586, "H_W": 0.683, "y_pred": 0.05 }, { "x": 0.325, "y": 0.537, "vx": -0.898, "vy": 0.439, "H_W": 0.683, "y_pred": 0.515 }, { "x": 0.877, "y": 0.427, "vx": -0.898, "vy": -0.439, "H_W": 0.683, "y_pred": 0.916 }, { "x": 0.571, "y": 0.609, "vx": 0.898, "vy": 0.439, "H_W": 0.683, "y_pred": 0.916 }, { "x": 0.534, "y": 0.681, "vx": -0.898, "vy": 0.439, "H_W": 0.683, "y_pred": 0.221 }, { "x": 0.361, "y": 0.753, "vx": 0.898, "vy": 0.439, "H_W": 0.683, "y_pred": 0.79 }, { "x": 0.191, "y": 0.211, "vx": -0.898, "vy": -0.439, "H_W": 0.683, "y_pred": 0.642 }, { "x": 0.744, "y": 0.825, "vx": -0.898, "vy": 0.439, "H_W": 0.683, "y_pred": 0.073 }, { "x": 0.704, "y": 0.139, "vx": 0.898, "vy": -0.439, "H_W": 0.683, "y_pred": 0.073 }, { "x": 0.138, "y": 0.929, "vx": 0.817, "vy": 0.576, "H_W": 0.683, "y_pred": 0.182 }, { "x": 0.544, "y": 0.288, "vx": -0.817, "vy": 0.576, "H_W": 0.683, "y_pred": 0.12 }, { "x": 0.773, "y": 0.354, "vx": 0.817, "vy": -0.576, "H_W": 0.683, "y_pred": 0.12 }, { "x": 0.593, "y": 0.363, "vx": -0.817, "vy": 0.576, "H_W": 0.683, "y_pred": 0.005 }, { "x": 0.725, "y": 0.279, "vx": 0.817, "vy": -0.576, "H_W": 0.683, "y_pred": 0.005 }, { "x": 0.43, "y": 0.708, "vx": -0.983, "vy": 0.186, "H_W": 0.683, "y_pred": 0.897 }, { "x": 0.846, "y": 0.854, "vx": -0.983, "vy": -0.186, "H_W": 0.683, "y_pred": 0.344 }, { "x": 0.737, "y": 0.417, "vx": 0.983, "vy": -0.186, "H_W": 0.683, "y_pred": 0.344 }, { "x": 0.304, "y": 0.105, "vx": 0.932, "vy": 0.363, "H_W": 0.683, "y_pred": 0.501 }, { "x": 0.194, "y": 0.96, "vx": -0.932, "vy": 0.363, "H_W": 0.683, "y_pred": 0.361 }, { "x": 0.62, "y": 0.557, "vx": -0.984, "vy": -0.179, "H_W": 0.683, "y_pred": 0.125 }, { "x": 0.523, "y": 0.43, "vx": 0.934, "vy": 0.357, "H_W": 0.683, "y_pred": 0.696 }, { "x": 0.465, "y": 0.112, "vx": -0.934, "vy": 0.357, "H_W": 0.683, "y_pred": 0.93 }, { "x": 0.546, "y": 0.206, "vx": 0.934, "vy": -0.357, "H_W": 0.683, "y_pred": 0.048 }, { "x": 0.106, "y": 0.35, "vx": 0.983, "vy": 0.181, "H_W": 0.683, "y_pred": 0.591 }, { "x": 0.309, "y": 0.777, "vx": -0.983, "vy": 0.181, "H_W": 0.683, "y_pred": 0.869 }, { "x": 0.337, "y": 0.351, "vx": 0.819, "vy": -0.573, "H_W": 0.683, "y_pred": 0.327 }, { "x": 0.343, "y": 1, "vx": -0.819, "vy": -0.573, "H_W": 0.683, "y_pred": 0.375 }, { "x": 0.298, "y": 0.296, "vx": 0.819, "vy": -0.573, "H_W": 0.683, "y_pred": 0.423 }, { "x": 0.382, "y": 0.944, "vx": -0.819, "vy": -0.573, "H_W": 0.683, "y_pred": 0.471 }, { "x": 0.259, "y": 0.24, "vx": 0.819, "vy": -0.573, "H_W": 0.683, "y_pred": 0.518 }, { "x": 0.421, "y": 0.888, "vx": -0.819, "vy": -0.573, "H_W": 0.683, "y_pred": 0.566 }, { "x": 0.9, "y": 0.464, "vx": 0.819, "vy": 0.573, "H_W": 0.683, "y_pred": 0.566 }, { "x": 0.22, "y": 0.185, "vx": 0.819, "vy": -0.573, "H_W": 0.683, "y_pred": 0.614 }, { "x": 0.46, "y": 0.833, "vx": -0.819, "vy": -0.573, "H_W": 0.683, "y_pred": 0.662 }, { "x": 0.861, "y": 0.519, "vx": 0.819, "vy": 0.573, "H_W": 0.683, "y_pred": 0.662 }, { "x": 0.181, "y": 0.129, "vx": 0.819, "vy": -0.573, "H_W": 0.683, "y_pred": 0.71 }, { "x": 0.499, "y": 0.777, "vx": -0.819, "vy": -0.573, "H_W": 0.683, "y_pred": 0.757 }, { "x": 0.822, "y": 0.575, "vx": 0.819, "vy": 0.573, "H_W": 0.683, "y_pred": 0.757 }, { "x": 0.142, "y": 0.073, "vx": 0.819, "vy": -0.573, "H_W": 0.683, "y_pred": 0.805 }, { "x": 0.538, "y": 0.721, "vx": -0.819, "vy": -0.573, "H_W": 0.683, "y_pred": 0.853 }, { "x": 0.783, "y": 0.63, "vx": 0.819, "vy": 0.573, "H_W": 0.683, "y_pred": 0.853 }, { "x": 0.103, "y": 0.018, "vx": 0.819, "vy": -0.573, "H_W": 0.683, "y_pred": 0.901 }, { "x": 0.577, "y": 0.666, "vx": -0.819, "vy": -0.573, "H_W": 0.683, "y_pred": 0.948 }, { "x": 0.744, "y": 0.686, "vx": 0.819, "vy": 0.573, "H_W": 0.683, "y_pred": 0.948 }, { "x": 0.726, "y": 0.001, "vx": 0.492, "vy": -0.871, "H_W": 0.683, "y_pred": 0.709 }, { "x": 0.482, "y": 0.053, "vx": -0.492, "vy": 0.871, "H_W": 0.683, "y_pred": 0.108 }, { "x": 0.553, "y": 0.218, "vx": -0.99, "vy": 0.143, "H_W": 0.683, "y_pred": 0.547 }, { "x": 0.615, "y": 0.968, "vx": 0.956, "vy": -0.295, "H_W": 0.683, "y_pred": 0.794 }, { "x": 0.155, "y": 0.272, "vx": 0.956, "vy": -0.295, "H_W": 0.683, "y_pred": 0.109 }, { "x": 0.305, "y": 0.423, "vx": -0.956, "vy": 0.295, "H_W": 0.683, "y_pred": 0.988 }, { "x": 0.757, "y": 0.935, "vx": -0.99, "vy": -0.144, "H_W": 0.683, "y_pred": 0.562 }, { "x": 0.837, "y": 0.596, "vx": 0.99, "vy": -0.144, "H_W": 0.683, "y_pred": 0.562 }, { "x": 0.866, "y": 0.633, "vx": -0.828, "vy": 0.561, "H_W": 0.683, "y_pred": 0.484 }, { "x": 0.417, "y": 0.049, "vx": 0.738, "vy": 0.674, "H_W": 0.683, "y_pred": 0.828 }, { "x": 0.393, "y": 0.36, "vx": -0.738, "vy": -0.674, "H_W": 0.683, "y_pred": 0.499 }, { "x": 0.797, "y": 0.77, "vx": 0.738, "vy": -0.674, "H_W": 0.683, "y_pred": 0.499 }, { "x": 0.165, "y": 0.295, "vx": 0.675, "vy": 0.738, "H_W": 0.683, "y_pred": 0.37 }, { "x": 0.747, "y": 0.035, "vx": -0.675, "vy": 0.738, "H_W": 0.683, "y_pred": 0.827 }, { "x": 0.248, "y": 0.494, "vx": 0.933, "vy": -0.359, "H_W": 0.683, "y_pred": 0.07 }, { "x": 0.248, "y": 0.354, "vx": -0.933, "vy": 0.359, "H_W": 0.683, "y_pred": 0.943 }, { "x": 0.744, "y": 0.799, "vx": -0.933, "vy": -0.359, "H_W": 0.683, "y_pred": 0.183 }, { "x": 0.76, "y": 0.048, "vx": 0.933, "vy": 0.359, "H_W": 0.683, "y_pred": 0.183 }, { "x": 0.255, "y": 0.924, "vx": 0.901, "vy": 0.434, "H_W": 0.683, "y_pred": 0.551 }, { "x": 0.293, "y": 0.052, "vx": -0.901, "vy": -0.434, "H_W": 0.683, "y_pred": 0.861 }, { "x": 0.842, "y": 0.972, "vx": -0.901, "vy": 0.434, "H_W": 0.683, "y_pred": 0.272 }, { "x": 0.61, "y": 0.003, "vx": 0.901, "vy": -0.434, "H_W": 0.683, "y_pred": 0.272 }, { "x": 0.487, "y": 0.045, "vx": -0.901, "vy": 0.434, "H_W": 0.683, "y_pred": 0.905 }, { "x": 0.188, "y": 0.886, "vx": 0.677, "vy": -0.736, "H_W": 0.683, "y_pred": 0.403 }, { "x": 0.72, "y": 0.848, "vx": -0.677, "vy": 0.736, "H_W": 0.683, "y_pred": 0.419 }, { "x": 0.323, "y": 0.641, "vx": 0.588, "vy": 0.809, "H_W": 0.683, "y_pred": 0.002 }, { "x": 0.759, "y": 0.577, "vx": -0.521, "vy": 0.854, "H_W": 0.683, "y_pred": 0.798 }, { "x": 0.8, "y": 0.701, "vx": 0.453, "vy": 0.892, "H_W": 0.683, "y_pred": 0.722 }, { "x": 0.471, "y": 0.803, "vx": -0.453, "vy": 0.892, "H_W": 0.683, "y_pred": 0.959 }, { "x": 0.298, "y": 0.718, "vx": 0.972, "vy": -0.235, "H_W": 0.683, "y_pred": 0.47 }, { "x": 0.136, "y": 0.164, "vx": -0.972, "vy": -0.235, "H_W": 0.683, "y_pred": 0.238 }, { "x": 0.569, "y": 0.39, "vx": -0.972, "vy": 0.235, "H_W": 0.683, "y_pred": 0.945 }, { "x": 0.563, "y": 0.502, "vx": 0.972, "vy": -0.235, "H_W": 0.683, "y_pred": 0.348 }, { "x": 0.564, "y": 0.338, "vx": 0.972, "vy": 0.236, "H_W": 0.683, "y_pred": 0.493 }, { "x": 0.125, "y": 0.916, "vx": 0.929, "vy": 0.37, "H_W": 0.683, "y_pred": 0.575 }, { "x": 0.378, "y": 0.212, "vx": -0.929, "vy": -0.37, "H_W": 0.683, "y_pred": 0.59 }, { "x": 0.865, "y": 0.602, "vx": -0.942, "vy": 0.337, "H_W": 0.683, "y_pred": 0.421 }, { "x": 0.5, "y": 0.169, "vx": -0.94, "vy": -0.341, "H_W": 0.683, "y_pred": 0.627 }, { "x": 0.45, "y": 0.084, "vx": 0.962, "vy": -0.273, "H_W": 0.683, "y_pred": 0.145 }, { "x": 0.493, "y": 0.273, "vx": -0.932, "vy": -0.363, "H_W": 0.683, "y_pred": 0.579 }, { "x": 0.631, "y": 0.852, "vx": 0.977, "vy": 0.214, "H_W": 0.683, "y_pred": 0.97 }, { "x": 0.136, "y": 0.329, "vx": 0.867, "vy": -0.499, "H_W": 0.683, "y_pred": 0.398 }, { "x": 0.468, "y": 0.846, "vx": -0.867, "vy": 0.499, "H_W": 0.683, "y_pred": 0.082 }, { "x": 0.204, "y": 0.068, "vx": 0.55, "vy": -0.835, "H_W": 0.683, "y_pred": 0.3 }, { "x": 0.474, "y": 0.923, "vx": -0.954, "vy": -0.299, "H_W": 0.683, "y_pred": 0.248 }, { "x": 0.45, "y": 0.934, "vx": 0.872, "vy": 0.489, "H_W": 0.683, "y_pred": 0.615 }, { "x": 0.144, "y": 0.087, "vx": -0.872, "vy": 0.489, "H_W": 0.683, "y_pred": 0.975 }, { "x": 0.28, "y": 0.949, "vx": -0.992, "vy": -0.123, "H_W": 0.683, "y_pred": 0.717 }, { "x": 0.182, "y": 0.605, "vx": 0.869, "vy": -0.494, "H_W": 0.683, "y_pred": 0.075 }, { "x": 0.417, "y": 0.56, "vx": -0.869, "vy": 0.494, "H_W": 0.683, "y_pred": 0.262 }, { "x": 0.318, "y": 0.142, "vx": 0.949, "vy": -0.315, "H_W": 0.683, "y_pred": 0.19 }, { "x": 0.153, "y": 0.601, "vx": -0.949, "vy": 0.315, "H_W": 0.683, "y_pred": 0.84 }, { "x": 0.623, "y": 0.657, "vx": -0.949, "vy": -0.315, "H_W": 0.683, "y_pred": 0.131 }, { "x": 0.436, "y": 0.828, "vx": 0.949, "vy": 0.315, "H_W": 0.683, "y_pred": 0.898 }, { "x": 0.505, "y": 0.313, "vx": -0.949, "vy": 0.315, "H_W": 0.683, "y_pred": 0.956 }, { "x": 0.31, "y": 0.828, "vx": 0.74, "vy": -0.673, "H_W": 0.683, "y_pred": 0.09 }, { "x": 0.498, "y": 0.759, "vx": -0.74, "vy": 0.673, "H_W": 0.683, "y_pred": 0.753 }, { "x": 0.776, "y": 0.916, "vx": -0.87, "vy": 0.494, "H_W": 0.683, "y_pred": 0.391 }, { "x": 0.626, "y": 0.08, "vx": 0.87, "vy": 0.494, "H_W": 0.683, "y_pred": 0.391 }, { "x": 0.833, "y": 0.655, "vx": 0.861, "vy": -0.508, "H_W": 0.683, "y_pred": 0.511 }, { "x": 0.204, "y": 0.58, "vx": 0.791, "vy": 0.612, "H_W": 0.683, "y_pred": 0.52 }, { "x": 0.521, "y": 0.022, "vx": -0.791, "vy": 0.612, "H_W": 0.683, "y_pred": 0.257 }, { "x": 0.666, "y": 0.392, "vx": 0.699, "vy": -0.715, "H_W": 0.683, "y_pred": 0.109 }, { "x": 0.208, "y": 0.705, "vx": -0.699, "vy": -0.715, "H_W": 0.683, "y_pred": 0.894 }, { "x": 0.798, "y": 0.866, "vx": 0.607, "vy": -0.795, "H_W": 0.683, "y_pred": 0.479 }, { "x": 0.224, "y": 0.992, "vx": -0.607, "vy": -0.795, "H_W": 0.683, "y_pred": 0.647 }, { "x": 0.754, "y": 0.882, "vx": 0.607, "vy": 0.795, "H_W": 0.683, "y_pred": 0.647 }, { "x": 0.268, "y": 0.756, "vx": -0.607, "vy": 0.795, "H_W": 0.683, "y_pred": 0.815 }, { "x": 0.733, "y": 0.321, "vx": 0.734, "vy": -0.68, "H_W": 0.683, "y_pred": 0.041 }, { "x": 0.573, "y": 0.249, "vx": -0.863, "vy": 0.505, "H_W": 0.683, "y_pred": 0.405 }, { "x": 0.664, "y": 0.331, "vx": -0.993, "vy": -0.116, "H_W": 0.683, "y_pred": 0.047 }, { "x": 0.531, "y": 0.742, "vx": 0.941, "vy": 0.337, "H_W": 0.683, "y_pred": 0.988 }, { "x": 0.545, "y": 0.136, "vx": -0.941, "vy": -0.339, "H_W": 0.683, "y_pred": 0.677 }, { "x": 0.591, "y": 0.277, "vx": -0.994, "vy": -0.11, "H_W": 0.683, "y_pred": 0.019 }, { "x": 0.544, "y": 0.705, "vx": 0.935, "vy": 0.355, "H_W": 0.683, "y_pred": 0.958 }, { "x": 0.691, "y": 0.907, "vx": -0.82, "vy": -0.572, "H_W": 0.683, "y_pred": 0.819 }, { "x": 0.63, "y": 0.442, "vx": 0.82, "vy": 0.572, "H_W": 0.683, "y_pred": 0.819 }, { "x": 0.838, "y": 0.653, "vx": -0.748, "vy": -0.664, "H_W": 0.683, "y_pred": 0.268 }, { "x": 0.331, "y": 0.967, "vx": 0.671, "vy": 0.741, "H_W": 0.683, "y_pred": 0.049 }, { "x": 0.542, "y": 0.647, "vx": -0.746, "vy": 0.666, "H_W": 0.683, "y_pred": 0.661 }, { "x": 0.588, "y": 0.323, "vx": 0.662, "vy": 0.749, "H_W": 0.683, "y_pred": 0.994 }, { "x": 0.411, "y": 0.168, "vx": -0.595, "vy": 0.804, "H_W": 0.683, "y_pred": 0.957 }, { "x": 0.629, "y": 0.037, "vx": 0.687, "vy": -0.726, "H_W": 0.683, "y_pred": 0.536 }, { "x": 0.263, "y": 0.324, "vx": -0.687, "vy": -0.726, "H_W": 0.683, "y_pred": 0.371 }]}